AUTHORS
CHANGELOG.txt
DESCRIPTION
LICENSE
MANIFEST.in
README.rst
setup.py
cmsplugin_googlemap/__init__.py
cmsplugin_googlemap/cms_plugins.py
cmsplugin_googlemap/forms.py
cmsplugin_googlemap/models.py
cmsplugin_googlemap.egg-info/PKG-INFO
cmsplugin_googlemap.egg-info/SOURCES.txt
cmsplugin_googlemap.egg-info/dependency_links.txt
cmsplugin_googlemap.egg-info/requires.txt
cmsplugin_googlemap.egg-info/top_level.txt
cmsplugin_googlemap/migrations/0001_initial.py
cmsplugin_googlemap/migrations/__init__.py
cmsplugin_googlemap/templates/cmsplugin_googlemap/googlemap.html
cmsplugin_googlemap/tests/__init__.py
cmsplugin_googlemap/tests/runtests.py
cmsplugin_googlemap/tests/south_settings.py
cmsplugin_googlemap/tests/test_settings.py
cmsplugin_googlemap/tests/urls.py