Metadata-Version: 1.0
Name: cmsplugin-googlemap
Version: 0.1.4
Summary: An app for integrating a google map in your cms layout.
